cloudbulkupload/__init__.py
cloudbulkupload/azure_blob.py
cloudbulkupload/bulkboto3.py
cloudbulkupload/exceptions.py
cloudbulkupload/google_storage.py
cloudbulkupload/transfer_path.py
cloudbulkupload-2.0.0.dist-info/licenses/LICENSE
cloudbulkupload-2.0.0.dist-info/METADATA
cloudbulkupload-2.0.0.dist-info/WHEEL
cloudbulkupload-2.0.0.dist-info/top_level.txt
cloudbulkupload-2.0.0.dist-info/RECORD
