Metadata-Version: 2.4
Name: cloudbulkupload
Version: 2.0.0
Summary: Python package for fast and parallel transferring a bulk of files to S3, Azure Blob Storage, and Google Cloud Storage
Home-page: https://github.com/dynamicdeploy/cloudbulkupload
Author: Dynamic Deploy. Credit: Amir Masoud Sefidian
Author-email: "Dynamic Deploy. Credit: Amir Masoud Sefidian" <dynamicdeploy@gmail.com>
Maintainer-email: "Dynamic Deploy. Credit: Amir Masoud Sefidian" <dynamicdeploy@gmail.com>
License-Expression: MIT
Project-URL: Homepage, https://github.com/dynamicdeploy/cloudbulkupload
Project-URL: Repository, https://github.com/dynamicdeploy/cloudbulkupload
Project-URL: Issues, https://github.com/dynamicdeploy/cloudbulkupload/issues
Keywords: Boto3,S3,Azure,Google Cloud,Blob Storage,Parallel,Multi-thread,Bulk,Boto,Bulk Boto,Bulk Boto3,Simple Storage Service,Minio,Amazon AWS S3,Microsoft Azure,Google Cloud Storage,Python,Async
Classifier: Development Status :: 5 - Production/Stable
Classifier: Intended Audience :: Developers
Classifier: Natural Language :: English
Classifier: Programming Language :: Python
Classifier: Programming Language :: Python :: 3
Classifier: Programming Language :: Python :: 3.6
Classifier: Programming Language :: Python :: 3.7
Classifier: Programming Language :: Python :: 3.8
Classifier: Programming Language :: Python :: 3.9
Classifier: Programming Language :: Python :: 3.10
Classifier: Operating System :: OS Independent
Requires-Python: >=3.11.0
License-File: LICENSE
Requires-Dist: boto3>=1.21.26
Requires-Dist: azure-storage-blob>=12.0.0
Requires-Dist: google-cloud-storage>=2.0.0
Requires-Dist: aiohttp>=3.8.0
Requires-Dist: tqdm
Provides-Extra: dev
Requires-Dist: isort; extra == "dev"
Requires-Dist: black; extra == "dev"
Provides-Extra: test
Requires-Dist: pytest; extra == "test"
Requires-Dist: pytest-cov; extra == "test"
Requires-Dist: python-dotenv; extra == "test"
Requires-Dist: azure-storage-blob>=12.0.0; extra == "test"
Requires-Dist: google-cloud-storage>=2.0.0; extra == "test"
Dynamic: author
Dynamic: home-page
Dynamic: license-file
Dynamic: requires-python
